ec_finder/__init__.py
ec_finder/ec_finder.py
ec_finder-0.1.data/scripts/ec-find
ec_finder-0.1.dist-info/AUTHORS.txt
ec_finder-0.1.dist-info/LICENSE.txt
ec_finder-0.1.dist-info/METADATA
ec_finder-0.1.dist-info/WHEEL
ec_finder-0.1.dist-info/top_level.txt
ec_finder-0.1.dist-info/RECORD
