Metadata-Version: 2.1
Name: ec-finder
Version: 0.1
Summary: Find suitable EC numbers from enzyme names
Home-page: https://github.com/ggonnella/ec_finder
Author: Giorgio Gonnella and and others (see CONTRIBUTORS)
Author-email: gonnella@zbh.uni-hamburg.de
License: ISC
Keywords: bioinformatics
Platform: UNKNOWN
Classifier: Development Status :: 5 - Production/Stable
Classifier: Environment :: Console
Classifier: Intended Audience :: Developers
Classifier: Intended Audience :: End Users/Desktop
Classifier: Intended Audience :: Science/Research
Classifier: License :: OSI Approved :: ISC License (ISCL)
Classifier: Operating System :: MacOS :: MacOS X
Classifier: Operating System :: POSIX :: Linux
Classifier: Programming Language :: Python :: 3 :: Only
Classifier: Topic :: Scientific/Engineering :: Bio-Informatics
Classifier: Topic :: Software Development :: Libraries
License-File: LICENSE.txt
License-File: AUTHORS.txt
Requires-Dist: loguru (>=0.5.1)
Requires-Dist: docopt (>=0.6.2)
Requires-Dist: sh (>=1.14.2)
Requires-Dist: thefuzz
Requires-Dist: PlatformDirs
Requires-Dist: python-Levenshtein
